myeda/__init__.py
myeda/report.py
myeda/core/__init__.py
myeda/core/missing.py
myeda/core/overview.py
myeda/core/statistics.py
myeda/viz/__init__.py
myeda/viz/visualization.py
myeda-0.1.14.dist-info/licenses/LICENSE
myeda-0.1.14.dist-info/METADATA
myeda-0.1.14.dist-info/WHEEL
myeda-0.1.14.dist-info/top_level.txt
myeda-0.1.14.dist-info/RECORD
