Metadata-Version: 2.4
Name: myeda
Version: 0.1.14
Summary: One-line Exploratory Data Analysis (EDA) library
Author: Khaja Mubashir Arsalan
License-Expression: MIT
Project-URL: Homepage, https://github.com/KHAJA-MUBASHIR-ARSALAN/myeda
Project-URL: Source, https://github.com/KHAJA-MUBASHIR-ARSALAN/myeda
Project-URL: Issues, https://github.com/KHAJA-MUBASHIR-ARSALAN/myeda/issues
Classifier: Programming Language :: Python :: 3
Classifier: Programming Language :: Python :: 3.9
Classifier: Programming Language :: Python :: 3.10
Classifier: Programming Language :: Python :: 3.11
Classifier: Operating System :: OS Independent
Requires-Python: >=3.9
License-File: LICENSE
Requires-Dist: pandas
Requires-Dist: matplotlib
Dynamic: license-file
